<annotation>
	<folder>images</folder>
	<filename>00000673.xml</filename>
	<path>L:/Dataset/Mine/Human/head_body/final\resized/labels/00000673.xml00000673.xml</path>
	<source>
		<database>Unknown</database>
	</source>
	<size>
		<width>960</width>
		<height>540</height>
		<depth>3</depth>
	</size>
	<segmented>0</segmented>
	<object>
		<name>person_head</name>
		<pose>Unspecified</pose>
		<truncated>0</truncated>
		<difficult>0</difficult>
		<bndbox>
			<xmin>29</xmin>
			<ymin>76</ymin>
			<xmax>44</xmax>
			<ymax>90</ymax>
		</bndbox>
	</object>
	<object>
		<name>person_vbox</name>
		<pose>Unspecified</pose>
		<truncated>0</truncated>
		<difficult>0</difficult>
		<bndbox>
			<xmin>23</xmin>
			<ymin>76</ymin>
			<xmax>49</xmax>
			<ymax>99</ymax>
		</bndbox>
	</object>
	<object>
		<name>person_head</name>
		<pose>Unspecified</pose>
		<truncated>0</truncated>
		<difficult>0</difficult>
		<bndbox>
			<xmin>196</xmin>
			<ymin>73</ymin>
			<xmax>209</xmax>
			<ymax>89</ymax>
		</bndbox>
	</object>
	<object>
		<name>person_vbox</name>
		<pose>Unspecified</pose>
		<truncated>0</truncated>
		<difficult>0</difficult>
		<bndbox>
			<xmin>179</xmin>
			<ymin>72</ymin>
			<xmax>211</xmax>
			<ymax>155</ymax>
		</bndbox>
	</object>
	<object>
		<name>person_head</name>
		<pose>Unspecified</pose>
		<truncated>0</truncated>
		<difficult>0</difficult>
		<bndbox>
			<xmin>73</xmin>
			<ymin>417</ymin>
			<xmax>109</xmax>
			<ymax>455</ymax>
		</bndbox>
	</object>
	<object>
		<name>person_vbox</name>
		<pose>Unspecified</pose>
		<truncated>0</truncated>
		<difficult>0</difficult>
		<bndbox>
			<xmin>60</xmin>
			<ymin>416</ymin>
			<xmax>146</xmax>
			<ymax>540</ymax>
		</bndbox>
	</object>
	<object>
		<name>person_head</name>
		<pose>Unspecified</pose>
		<truncated>0</truncated>
		<difficult>0</difficult>
		<bndbox>
			<xmin>234</xmin>
			<ymin>75</ymin>
			<xmax>253</xmax>
			<ymax>95</ymax>
		</bndbox>
	</object>
	<object>
		<name>person_vbox</name>
		<pose>Unspecified</pose>
		<truncated>0</truncated>
		<difficult>0</difficult>
		<bndbox>
			<xmin>225</xmin>
			<ymin>75</ymin>
			<xmax>265</xmax>
			<ymax>172</ymax>
		</bndbox>
	</object>
	<object>
		<name>person_head</name>
		<pose>Unspecified</pose>
		<truncated>0</truncated>
		<difficult>0</difficult>
		<bndbox>
			<xmin>175</xmin>
			<ymin>451</ymin>
			<xmax>207</xmax>
			<ymax>488</ymax>
		</bndbox>
	</object>
	<object>
		<name>person_vbox</name>
		<pose>Unspecified</pose>
		<truncated>0</truncated>
		<difficult>0</difficult>
		<bndbox>
			<xmin>160</xmin>
			<ymin>451</ymin>
			<xmax>239</xmax>
			<ymax>540</ymax>
		</bndbox>
	</object>
	<object>
		<name>person_head</name>
		<pose>Unspecified</pose>
		<truncated>0</truncated>
		<difficult>0</difficult>
		<bndbox>
			<xmin>382</xmin>
			<ymin>87</ymin>
			<xmax>396</xmax>
			<ymax>101</ymax>
		</bndbox>
	</object>
	<object>
		<name>person_vbox</name>
		<pose>Unspecified</pose>
		<truncated>0</truncated>
		<difficult>0</difficult>
		<bndbox>
			<xmin>373</xmin>
			<ymin>87</ymin>
			<xmax>400</xmax>
			<ymax>119</ymax>
		</bndbox>
	</object>
	<object>
		<name>person_head</name>
		<pose>Unspecified</pose>
		<truncated>0</truncated>
		<difficult>0</difficult>
		<bndbox>
			<xmin>407</xmin>
			<ymin>81</ymin>
			<xmax>421</xmax>
			<ymax>97</ymax>
		</bndbox>
	</object>
	<object>
		<name>person_vbox</name>
		<pose>Unspecified</pose>
		<truncated>0</truncated>
		<difficult>0</difficult>
		<bndbox>
			<xmin>400</xmin>
			<ymin>81</ymin>
			<xmax>424</xmax>
			<ymax>118</ymax>
		</bndbox>
	</object>
	<object>
		<name>person_head</name>
		<pose>Unspecified</pose>
		<truncated>0</truncated>
		<difficult>0</difficult>
		<bndbox>
			<xmin>425</xmin>
			<ymin>74</ymin>
			<xmax>442</xmax>
			<ymax>93</ymax>
		</bndbox>
	</object>
	<object>
		<name>person_vbox</name>
		<pose>Unspecified</pose>
		<truncated>0</truncated>
		<difficult>0</difficult>
		<bndbox>
			<xmin>411</xmin>
			<ymin>74</ymin>
			<xmax>447</xmax>
			<ymax>122</ymax>
		</bndbox>
	</object>
	<object>
		<name>person_head</name>
		<pose>Unspecified</pose>
		<truncated>0</truncated>
		<difficult>0</difficult>
		<bndbox>
			<xmin>448</xmin>
			<ymin>131</ymin>
			<xmax>465</xmax>
			<ymax>153</ymax>
		</bndbox>
	</object>
	<object>
		<name>person_vbox</name>
		<pose>Unspecified</pose>
		<truncated>0</truncated>
		<difficult>0</difficult>
		<bndbox>
			<xmin>425</xmin>
			<ymin>130</ymin>
			<xmax>473</xmax>
			<ymax>249</ymax>
		</bndbox>
	</object>
	<object>
		<name>person_head</name>
		<pose>Unspecified</pose>
		<truncated>0</truncated>
		<difficult>0</difficult>
		<bndbox>
			<xmin>509</xmin>
			<ymin>87</ymin>
			<xmax>523</xmax>
			<ymax>103</ymax>
		</bndbox>
	</object>
	<object>
		<name>person_vbox</name>
		<pose>Unspecified</pose>
		<truncated>0</truncated>
		<difficult>0</difficult>
		<bndbox>
			<xmin>501</xmin>
			<ymin>86</ymin>
			<xmax>529</xmax>
			<ymax>121</ymax>
		</bndbox>
	</object>
	<object>
		<name>person_head</name>
		<pose>Unspecified</pose>
		<truncated>0</truncated>
		<difficult>0</difficult>
		<bndbox>
			<xmin>528</xmin>
			<ymin>82</ymin>
			<xmax>545</xmax>
			<ymax>101</ymax>
		</bndbox>
	</object>
	<object>
		<name>person_vbox</name>
		<pose>Unspecified</pose>
		<truncated>0</truncated>
		<difficult>0</difficult>
		<bndbox>
			<xmin>519</xmin>
			<ymin>82</ymin>
			<xmax>550</xmax>
			<ymax>145</ymax>
		</bndbox>
	</object>
	<object>
		<name>person_head</name>
		<pose>Unspecified</pose>
		<truncated>0</truncated>
		<difficult>0</difficult>
		<bndbox>
			<xmin>554</xmin>
			<ymin>76</ymin>
			<xmax>569</xmax>
			<ymax>93</ymax>
		</bndbox>
	</object>
	<object>
		<name>person_vbox</name>
		<pose>Unspecified</pose>
		<truncated>0</truncated>
		<difficult>0</difficult>
		<bndbox>
			<xmin>545</xmin>
			<ymin>75</ymin>
			<xmax>584</xmax>
			<ymax>185</ymax>
		</bndbox>
	</object>
	<object>
		<name>person_head</name>
		<pose>Unspecified</pose>
		<truncated>0</truncated>
		<difficult>0</difficult>
		<bndbox>
			<xmin>572</xmin>
			<ymin>104</ymin>
			<xmax>590</xmax>
			<ymax>125</ymax>
		</bndbox>
	</object>
	<object>
		<name>person_vbox</name>
		<pose>Unspecified</pose>
		<truncated>0</truncated>
		<difficult>0</difficult>
		<bndbox>
			<xmin>565</xmin>
			<ymin>104</ymin>
			<xmax>596</xmax>
			<ymax>202</ymax>
		</bndbox>
	</object>
	<object>
		<name>person_head</name>
		<pose>Unspecified</pose>
		<truncated>0</truncated>
		<difficult>0</difficult>
		<bndbox>
			<xmin>588</xmin>
			<ymin>129</ymin>
			<xmax>609</xmax>
			<ymax>150</ymax>
		</bndbox>
	</object>
	<object>
		<name>person_vbox</name>
		<pose>Unspecified</pose>
		<truncated>0</truncated>
		<difficult>0</difficult>
		<bndbox>
			<xmin>578</xmin>
			<ymin>129</ymin>
			<xmax>614</xmax>
			<ymax>236</ymax>
		</bndbox>
	</object>
	<object>
		<name>person_head</name>
		<pose>Unspecified</pose>
		<truncated>0</truncated>
		<difficult>0</difficult>
		<bndbox>
			<xmin>604</xmin>
			<ymin>161</ymin>
			<xmax>620</xmax>
			<ymax>181</ymax>
		</bndbox>
	</object>
	<object>
		<name>person_vbox</name>
		<pose>Unspecified</pose>
		<truncated>0</truncated>
		<difficult>0</difficult>
		<bndbox>
			<xmin>592</xmin>
			<ymin>161</ymin>
			<xmax>628</xmax>
			<ymax>272</ymax>
		</bndbox>
	</object>
	<object>
		<name>person_head</name>
		<pose>Unspecified</pose>
		<truncated>0</truncated>
		<difficult>0</difficult>
		<bndbox>
			<xmin>623</xmin>
			<ymin>189</ymin>
			<xmax>644</xmax>
			<ymax>211</ymax>
		</bndbox>
	</object>
	<object>
		<name>person_vbox</name>
		<pose>Unspecified</pose>
		<truncated>0</truncated>
		<difficult>0</difficult>
		<bndbox>
			<xmin>614</xmin>
			<ymin>189</ymin>
			<xmax>652</xmax>
			<ymax>309</ymax>
		</bndbox>
	</object>
	<object>
		<name>person_head</name>
		<pose>Unspecified</pose>
		<truncated>0</truncated>
		<difficult>0</difficult>
		<bndbox>
			<xmin>649</xmin>
			<ymin>227</ymin>
			<xmax>667</xmax>
			<ymax>248</ymax>
		</bndbox>
	</object>
	<object>
		<name>person_vbox</name>
		<pose>Unspecified</pose>
		<truncated>0</truncated>
		<difficult>0</difficult>
		<bndbox>
			<xmin>631</xmin>
			<ymin>227</ymin>
			<xmax>669</xmax>
			<ymax>352</ymax>
		</bndbox>
	</object>
	<object>
		<name>person_head</name>
		<pose>Unspecified</pose>
		<truncated>0</truncated>
		<difficult>0</difficult>
		<bndbox>
			<xmin>661</xmin>
			<ymin>245</ymin>
			<xmax>682</xmax>
			<ymax>266</ymax>
		</bndbox>
	</object>
	<object>
		<name>person_vbox</name>
		<pose>Unspecified</pose>
		<truncated>0</truncated>
		<difficult>0</difficult>
		<bndbox>
			<xmin>652</xmin>
			<ymin>244</ymin>
			<xmax>699</xmax>
			<ymax>379</ymax>
		</bndbox>
	</object>
	<object>
		<name>person_head</name>
		<pose>Unspecified</pose>
		<truncated>0</truncated>
		<difficult>0</difficult>
		<bndbox>
			<xmin>693</xmin>
			<ymin>291</ymin>
			<xmax>715</xmax>
			<ymax>314</ymax>
		</bndbox>
	</object>
	<object>
		<name>person_vbox</name>
		<pose>Unspecified</pose>
		<truncated>0</truncated>
		<difficult>0</difficult>
		<bndbox>
			<xmin>676</xmin>
			<ymin>290</ymin>
			<xmax>721</xmax>
			<ymax>428</ymax>
		</bndbox>
	</object>
	<object>
		<name>person_head</name>
		<pose>Unspecified</pose>
		<truncated>0</truncated>
		<difficult>0</difficult>
		<bndbox>
			<xmin>716</xmin>
			<ymin>340</ymin>
			<xmax>739</xmax>
			<ymax>369</ymax>
		</bndbox>
	</object>
	<object>
		<name>person_vbox</name>
		<pose>Unspecified</pose>
		<truncated>0</truncated>
		<difficult>0</difficult>
		<bndbox>
			<xmin>690</xmin>
			<ymin>340</ymin>
			<xmax>747</xmax>
			<ymax>489</ymax>
		</bndbox>
	</object>
	<object>
		<name>person_head</name>
		<pose>Unspecified</pose>
		<truncated>0</truncated>
		<difficult>0</difficult>
		<bndbox>
			<xmin>760</xmin>
			<ymin>380</ymin>
			<xmax>785</xmax>
			<ymax>412</ymax>
		</bndbox>
	</object>
	<object>
		<name>person_vbox</name>
		<pose>Unspecified</pose>
		<truncated>0</truncated>
		<difficult>0</difficult>
		<bndbox>
			<xmin>727</xmin>
			<ymin>380</ymin>
			<xmax>796</xmax>
			<ymax>540</ymax>
		</bndbox>
	</object>
	<object>
		<name>person_head</name>
		<pose>Unspecified</pose>
		<truncated>0</truncated>
		<difficult>0</difficult>
		<bndbox>
			<xmin>217</xmin>
			<ymin>81</ymin>
			<xmax>225</xmax>
			<ymax>90</ymax>
		</bndbox>
	</object>
	<object>
		<name>person_vbox</name>
		<pose>Unspecified</pose>
		<truncated>0</truncated>
		<difficult>0</difficult>
		<bndbox>
			<xmin>214</xmin>
			<ymin>81</ymin>
			<xmax>229</xmax>
			<ymax>141</ymax>
		</bndbox>
	</object>
	<object>
		<name>person_head</name>
		<pose>Unspecified</pose>
		<truncated>0</truncated>
		<difficult>0</difficult>
		<bndbox>
			<xmin>262</xmin>
			<ymin>83</ymin>
			<xmax>274</xmax>
			<ymax>96</ymax>
		</bndbox>
	</object>
	<object>
		<name>person_vbox</name>
		<pose>Unspecified</pose>
		<truncated>0</truncated>
		<difficult>0</difficult>
		<bndbox>
			<xmin>262</xmin>
			<ymin>83</ymin>
			<xmax>284</xmax>
			<ymax>146</ymax>
		</bndbox>
	</object>
	<object>
		<name>person_head</name>
		<pose>Unspecified</pose>
		<truncated>0</truncated>
		<difficult>0</difficult>
		<bndbox>
			<xmin>282</xmin>
			<ymin>78</ymin>
			<xmax>293</xmax>
			<ymax>89</ymax>
		</bndbox>
	</object>
	<object>
		<name>person_vbox</name>
		<pose>Unspecified</pose>
		<truncated>0</truncated>
		<difficult>0</difficult>
		<bndbox>
			<xmin>279</xmin>
			<ymin>78</ymin>
			<xmax>309</xmax>
			<ymax>147</ymax>
		</bndbox>
	</object>
	<object>
		<name>person_head</name>
		<pose>Unspecified</pose>
		<truncated>0</truncated>
		<difficult>0</difficult>
		<bndbox>
			<xmin>325</xmin>
			<ymin>89</ymin>
			<xmax>335</xmax>
			<ymax>100</ymax>
		</bndbox>
	</object>
	<object>
		<name>person_vbox</name>
		<pose>Unspecified</pose>
		<truncated>0</truncated>
		<difficult>0</difficult>
		<bndbox>
			<xmin>318</xmin>
			<ymin>89</ymin>
			<xmax>337</xmax>
			<ymax>142</ymax>
		</bndbox>
	</object>
	<object>
		<name>person_head</name>
		<pose>Unspecified</pose>
		<truncated>0</truncated>
		<difficult>0</difficult>
		<bndbox>
			<xmin>366</xmin>
			<ymin>94</ymin>
			<xmax>370</xmax>
			<ymax>98</ymax>
		</bndbox>
	</object>
	<object>
		<name>person_vbox</name>
		<pose>Unspecified</pose>
		<truncated>0</truncated>
		<difficult>0</difficult>
		<bndbox>
			<xmin>360</xmin>
			<ymin>93</ymin>
			<xmax>373</xmax>
			<ymax>126</ymax>
		</bndbox>
	</object>
	<object>
		<name>person_head</name>
		<pose>Unspecified</pose>
		<truncated>0</truncated>
		<difficult>0</difficult>
		<bndbox>
			<xmin>424</xmin>
			<ymin>101</ymin>
			<xmax>441</xmax>
			<ymax>121</ymax>
		</bndbox>
	</object>
	<object>
		<name>person_vbox</name>
		<pose>Unspecified</pose>
		<truncated>0</truncated>
		<difficult>0</difficult>
		<bndbox>
			<xmin>425</xmin>
			<ymin>101</ymin>
			<xmax>460</xmax>
			<ymax>151</ymax>
		</bndbox>
	</object>
	<object>
		<name>person_head</name>
		<pose>Unspecified</pose>
		<truncated>0</truncated>
		<difficult>0</difficult>
		<bndbox>
			<xmin>452</xmin>
			<ymin>80</ymin>
			<xmax>463</xmax>
			<ymax>90</ymax>
		</bndbox>
	</object>
	<object>
		<name>person_vbox</name>
		<pose>Unspecified</pose>
		<truncated>0</truncated>
		<difficult>0</difficult>
		<bndbox>
			<xmin>446</xmin>
			<ymin>80</ymin>
			<xmax>472</xmax>
			<ymax>121</ymax>
		</bndbox>
	</object>
	<object>
		<name>person_head</name>
		<pose>Unspecified</pose>
		<truncated>0</truncated>
		<difficult>0</difficult>
		<bndbox>
			<xmin>489</xmin>
			<ymin>98</ymin>
			<xmax>494</xmax>
			<ymax>104</ymax>
		</bndbox>
	</object>
	<object>
		<name>person_vbox</name>
		<pose>Unspecified</pose>
		<truncated>0</truncated>
		<difficult>0</difficult>
		<bndbox>
			<xmin>485</xmin>
			<ymin>98</ymin>
			<xmax>495</xmax>
			<ymax>118</ymax>
		</bndbox>
	</object>
	<object>
		<name>person_head</name>
		<pose>Unspecified</pose>
		<truncated>0</truncated>
		<difficult>0</difficult>
		<bndbox>
			<xmin>500</xmin>
			<ymin>100</ymin>
			<xmax>505</xmax>
			<ymax>106</ymax>
		</bndbox>
	</object>
	<object>
		<name>person_vbox</name>
		<pose>Unspecified</pose>
		<truncated>0</truncated>
		<difficult>0</difficult>
		<bndbox>
			<xmin>496</xmin>
			<ymin>99</ymin>
			<xmax>505</xmax>
			<ymax>120</ymax>
		</bndbox>
	</object>
	<object>
		<name>person_head</name>
		<pose>Unspecified</pose>
		<truncated>0</truncated>
		<difficult>0</difficult>
		<bndbox>
			<xmin>583</xmin>
			<ymin>91</ymin>
			<xmax>590</xmax>
			<ymax>100</ymax>
		</bndbox>
	</object>
	<object>
		<name>person_vbox</name>
		<pose>Unspecified</pose>
		<truncated>0</truncated>
		<difficult>0</difficult>
		<bndbox>
			<xmin>581</xmin>
			<ymin>91</ymin>
			<xmax>596</xmax>
			<ymax>112</ymax>
		</bndbox>
	</object>
	<object>
		<name>person_head</name>
		<pose>Unspecified</pose>
		<truncated>0</truncated>
		<difficult>0</difficult>
		<bndbox>
			<xmin>610</xmin>
			<ymin>100</ymin>
			<xmax>615</xmax>
			<ymax>106</ymax>
		</bndbox>
	</object>
	<object>
		<name>person_vbox</name>
		<pose>Unspecified</pose>
		<truncated>0</truncated>
		<difficult>0</difficult>
		<bndbox>
			<xmin>604</xmin>
			<ymin>100</ymin>
			<xmax>618</xmax>
			<ymax>114</ymax>
		</bndbox>
	</object>
	<object>
		<name>person_head</name>
		<pose>Unspecified</pose>
		<truncated>0</truncated>
		<difficult>0</difficult>
		<bndbox>
			<xmin>626</xmin>
			<ymin>99</ymin>
			<xmax>632</xmax>
			<ymax>106</ymax>
		</bndbox>
	</object>
	<object>
		<name>person_vbox</name>
		<pose>Unspecified</pose>
		<truncated>0</truncated>
		<difficult>0</difficult>
		<bndbox>
			<xmin>619</xmin>
			<ymin>98</ymin>
			<xmax>639</xmax>
			<ymax>145</ymax>
		</bndbox>
	</object>
	<object>
		<name>person_head</name>
		<pose>Unspecified</pose>
		<truncated>0</truncated>
		<difficult>0</difficult>
		<bndbox>
			<xmin>641</xmin>
			<ymin>95</ymin>
			<xmax>650</xmax>
			<ymax>103</ymax>
		</bndbox>
	</object>
	<object>
		<name>person_vbox</name>
		<pose>Unspecified</pose>
		<truncated>0</truncated>
		<difficult>0</difficult>
		<bndbox>
			<xmin>633</xmin>
			<ymin>95</ymin>
			<xmax>650</xmax>
			<ymax>141</ymax>
		</bndbox>
	</object>
	<object>
		<name>person_head</name>
		<pose>Unspecified</pose>
		<truncated>0</truncated>
		<difficult>0</difficult>
		<bndbox>
			<xmin>655</xmin>
			<ymin>102</ymin>
			<xmax>664</xmax>
			<ymax>110</ymax>
		</bndbox>
	</object>
	<object>
		<name>person_vbox</name>
		<pose>Unspecified</pose>
		<truncated>0</truncated>
		<difficult>0</difficult>
		<bndbox>
			<xmin>646</xmin>
			<ymin>101</ymin>
			<xmax>664</xmax>
			<ymax>143</ymax>
		</bndbox>
	</object>
	<object>
		<name>person_head</name>
		<pose>Unspecified</pose>
		<truncated>0</truncated>
		<difficult>0</difficult>
		<bndbox>
			<xmin>334</xmin>
			<ymin>92</ymin>
			<xmax>339</xmax>
			<ymax>100</ymax>
		</bndbox>
	</object>
	<object>
		<name>person_vbox</name>
		<pose>Unspecified</pose>
		<truncated>0</truncated>
		<difficult>0</difficult>
		<bndbox>
			<xmin>334</xmin>
			<ymin>91</ymin>
			<xmax>344</xmax>
			<ymax>134</ymax>
		</bndbox>
	</object>
	<object>
		<name>person_head</name>
		<pose>Unspecified</pose>
		<truncated>0</truncated>
		<difficult>0</difficult>
		<bndbox>
			<xmin>0</xmin>
			<ymin>59</ymin>
			<xmax>12</xmax>
			<ymax>72</ymax>
		</bndbox>
	</object>
	<object>
		<name>person_vbox</name>
		<pose>Unspecified</pose>
		<truncated>0</truncated>
		<difficult>0</difficult>
		<bndbox>
			<xmin>0</xmin>
			<ymin>58</ymin>
			<xmax>20</xmax>
			<ymax>98</ymax>
		</bndbox>
	</object>
	<object>
		<name>person_head</name>
		<pose>Unspecified</pose>
		<truncated>0</truncated>
		<difficult>0</difficult>
		<bndbox>
			<xmin>19</xmin>
			<ymin>73</ymin>
			<xmax>28</xmax>
			<ymax>84</ymax>
		</bndbox>
	</object>
	<object>
		<name>person_vbox</name>
		<pose>Unspecified</pose>
		<truncated>0</truncated>
		<difficult>0</difficult>
		<bndbox>
			<xmin>16</xmin>
			<ymin>73</ymin>
			<xmax>28</xmax>
			<ymax>98</ymax>
		</bndbox>
	</object>
	
</annotation>	