<annotation>
	<folder>images</folder>
	<filename>00000792.xml</filename>
	<path>L:/Dataset/Mine/Human/head_body/final\resized/labels/00000792.xml00000792.xml</path>
	<source>
		<database>Unknown</database>
	</source>
	<size>
		<width>960</width>
		<height>540</height>
		<depth>3</depth>
	</size>
	<segmented>0</segmented>
	<object>
		<name>person_head</name>
		<pose>Unspecified</pose>
		<truncated>0</truncated>
		<difficult>0</difficult>
		<bndbox>
			<xmin>289</xmin>
			<ymin>82</ymin>
			<xmax>301</xmax>
			<ymax>94</ymax>
		</bndbox>
	</object>
	<object>
		<name>person_vbox</name>
		<pose>Unspecified</pose>
		<truncated>0</truncated>
		<difficult>0</difficult>
		<bndbox>
			<xmin>276</xmin>
			<ymin>83</ymin>
			<xmax>308</xmax>
			<ymax>152</ymax>
		</bndbox>
	</object>
	<object>
		<name>person_head</name>
		<pose>Unspecified</pose>
		<truncated>0</truncated>
		<difficult>0</difficult>
		<bndbox>
			<xmin>369</xmin>
			<ymin>86</ymin>
			<xmax>379</xmax>
			<ymax>98</ymax>
		</bndbox>
	</object>
	<object>
		<name>person_vbox</name>
		<pose>Unspecified</pose>
		<truncated>0</truncated>
		<difficult>0</difficult>
		<bndbox>
			<xmin>363</xmin>
			<ymin>87</ymin>
			<xmax>381</xmax>
			<ymax>148</ymax>
		</bndbox>
	</object>
	<object>
		<name>person_head</name>
		<pose>Unspecified</pose>
		<truncated>0</truncated>
		<difficult>0</difficult>
		<bndbox>
			<xmin>380</xmin>
			<ymin>91</ymin>
			<xmax>392</xmax>
			<ymax>103</ymax>
		</bndbox>
	</object>
	<object>
		<name>person_vbox</name>
		<pose>Unspecified</pose>
		<truncated>0</truncated>
		<difficult>0</difficult>
		<bndbox>
			<xmin>375</xmin>
			<ymin>91</ymin>
			<xmax>397</xmax>
			<ymax>121</ymax>
		</bndbox>
	</object>
	<object>
		<name>person_head</name>
		<pose>Unspecified</pose>
		<truncated>0</truncated>
		<difficult>0</difficult>
		<bndbox>
			<xmin>682</xmin>
			<ymin>94</ymin>
			<xmax>692</xmax>
			<ymax>104</ymax>
		</bndbox>
	</object>
	<object>
		<name>person_vbox</name>
		<pose>Unspecified</pose>
		<truncated>0</truncated>
		<difficult>0</difficult>
		<bndbox>
			<xmin>671</xmin>
			<ymin>94</ymin>
			<xmax>697</xmax>
			<ymax>116</ymax>
		</bndbox>
	</object>
	<object>
		<name>person_head</name>
		<pose>Unspecified</pose>
		<truncated>0</truncated>
		<difficult>0</difficult>
		<bndbox>
			<xmin>651</xmin>
			<ymin>96</ymin>
			<xmax>664</xmax>
			<ymax>108</ymax>
		</bndbox>
	</object>
	<object>
		<name>person_vbox</name>
		<pose>Unspecified</pose>
		<truncated>0</truncated>
		<difficult>0</difficult>
		<bndbox>
			<xmin>647</xmin>
			<ymin>96</ymin>
			<xmax>671</xmax>
			<ymax>151</ymax>
		</bndbox>
	</object>
	<object>
		<name>person_head</name>
		<pose>Unspecified</pose>
		<truncated>0</truncated>
		<difficult>0</difficult>
		<bndbox>
			<xmin>433</xmin>
			<ymin>79</ymin>
			<xmax>447</xmax>
			<ymax>96</ymax>
		</bndbox>
	</object>
	<object>
		<name>person_vbox</name>
		<pose>Unspecified</pose>
		<truncated>0</truncated>
		<difficult>0</difficult>
		<bndbox>
			<xmin>413</xmin>
			<ymin>77</ymin>
			<xmax>463</xmax>
			<ymax>191</ymax>
		</bndbox>
	</object>
	<object>
		<name>person_head</name>
		<pose>Unspecified</pose>
		<truncated>0</truncated>
		<difficult>0</difficult>
		<bndbox>
			<xmin>457</xmin>
			<ymin>143</ymin>
			<xmax>473</xmax>
			<ymax>166</ymax>
		</bndbox>
	</object>
	<object>
		<name>person_vbox</name>
		<pose>Unspecified</pose>
		<truncated>0</truncated>
		<difficult>0</difficult>
		<bndbox>
			<xmin>442</xmin>
			<ymin>142</ymin>
			<xmax>488</xmax>
			<ymax>256</ymax>
		</bndbox>
	</object>
	<object>
		<name>person_head</name>
		<pose>Unspecified</pose>
		<truncated>0</truncated>
		<difficult>0</difficult>
		<bndbox>
			<xmin>475</xmin>
			<ymin>202</ymin>
			<xmax>492</xmax>
			<ymax>226</ymax>
		</bndbox>
	</object>
	<object>
		<name>person_vbox</name>
		<pose>Unspecified</pose>
		<truncated>0</truncated>
		<difficult>0</difficult>
		<bndbox>
			<xmin>449</xmin>
			<ymin>204</ymin>
			<xmax>511</xmax>
			<ymax>327</ymax>
		</bndbox>
	</object>
	<object>
		<name>person_head</name>
		<pose>Unspecified</pose>
		<truncated>0</truncated>
		<difficult>0</difficult>
		<bndbox>
			<xmin>489</xmin>
			<ymin>356</ymin>
			<xmax>518</xmax>
			<ymax>384</ymax>
		</bndbox>
	</object>
	<object>
		<name>person_vbox</name>
		<pose>Unspecified</pose>
		<truncated>0</truncated>
		<difficult>0</difficult>
		<bndbox>
			<xmin>477</xmin>
			<ymin>356</ymin>
			<xmax>537</xmax>
			<ymax>488</ymax>
		</bndbox>
	</object>
	<object>
		<name>person_head</name>
		<pose>Unspecified</pose>
		<truncated>0</truncated>
		<difficult>0</difficult>
		<bndbox>
			<xmin>308</xmin>
			<ymin>84</ymin>
			<xmax>317</xmax>
			<ymax>95</ymax>
		</bndbox>
	</object>
	<object>
		<name>person_vbox</name>
		<pose>Unspecified</pose>
		<truncated>0</truncated>
		<difficult>0</difficult>
		<bndbox>
			<xmin>305</xmin>
			<ymin>82</ymin>
			<xmax>325</xmax>
			<ymax>145</ymax>
		</bndbox>
	</object>
	<object>
		<name>person_head</name>
		<pose>Unspecified</pose>
		<truncated>0</truncated>
		<difficult>0</difficult>
		<bndbox>
			<xmin>254</xmin>
			<ymin>85</ymin>
			<xmax>264</xmax>
			<ymax>95</ymax>
		</bndbox>
	</object>
	<object>
		<name>person_vbox</name>
		<pose>Unspecified</pose>
		<truncated>0</truncated>
		<difficult>0</difficult>
		<bndbox>
			<xmin>244</xmin>
			<ymin>85</ymin>
			<xmax>274</xmax>
			<ymax>145</ymax>
		</bndbox>
	</object>
	
</annotation>	